{"inkVersion":21,"root":[["^Okay, we are finally done. Have you got that thing decrypted yet?","\n","^Affirmative, but a call from headquarters has come through.","\n","^Right…well put it through.","\n","^Ah finally reached you. How has your mission gone so far?","\n","^Terribly. I haven’t found anyone and there is something else, here.","\n","^That doesn’t sound right… What station are you at?","\n","^Orbital station, G-35t0","\n","^You're meant to be at “C-091 get there immediately. You're currently at a construction site.","\n","^Oh… damn. Okay leaving immediately? I suppose the monster noises I heard would have been the station being built.","\n",["done",{"#f":5,"#n":"g-0"}],null],"done",{"#f":1}],"listDefs":{}}